zpp_logs/__init__.py
zpp_logs/core.py
zpp_logs/jinja_utils.py
zpp_logs/levels.py
zpp_logs/handlers/__init__.py
zpp_logs/handlers/base.py
zpp_logs/handlers/console.py
zpp_logs/handlers/database.py
zpp_logs/handlers/file.py
zpp_logs/handlers/resend.py
zpp_logs/handlers/smtp.py
zpp_logs/handlers/webhook.py
zpp_logs-2.1.1.dist-info/licenses/LICENSE
zpp_logs-2.1.1.dist-info/METADATA
zpp_logs-2.1.1.dist-info/WHEEL
zpp_logs-2.1.1.dist-info/top_level.txt
zpp_logs-2.1.1.dist-info/RECORD
