Metadata-Version: 2.4
Name: zpp_logs
Version: 2.1.1
Summary: Module de gestion de logs
Home-page: https://github.com/ZephyrOff/zpp_logs
Author: ZephyrOff <contact@apajak.fr>
License: MIT License
Project-URL: Documentation, https://github.com/ZephyrOff/zpp_logs
Keywords: logs module zephyroff
Platform: ALL
Classifier: Development Status :: 5 - Production/Stable
Classifier: Environment :: Console
Classifier: License :: OSI Approved :: MIT License
Classifier: Programming Language :: Python :: 3
License-File: LICENSE
Requires-Dist: psutil
Requires-Dist: impmagic
Requires-Dist: zpp_color
Requires-Dist: pyyaml
Requires-Dist: jinja2
Requires-Dist: requests
Requires-Dist: SQLAlchemy
Dynamic: author
Dynamic: classifier
Dynamic: description
Dynamic: description-content-type
Dynamic: home-page
Dynamic: keywords
Dynamic: license
Dynamic: license-file
Dynamic: platform
Dynamic: project-url
Dynamic: requires-dist
Dynamic: summary
